Metadata-Version: 2.1
Name: apexpro-mod
Version: 1.1.8
Summary: Python3 Apexpro HTTP/WebSocket API Connector
Home-page: https://github.com/xxx
Author: Dexter Dickinson
Author-email: xxx@apexpro.com
License: MIT License
Keywords: apexpro api connector
Classifier: Development Status :: 4 - Beta
Classifier: Intended Audience :: Developers
Classifier: Topic :: Software Development :: Libraries :: Python Modules
Classifier: License :: OSI Approved :: MIT License
Classifier: Programming Language :: Python :: 3.6
Classifier: Programming Language :: Python :: 3.7
Classifier: Programming Language :: Python :: 3.8
Classifier: Programming Language :: Python :: 3.9
Requires-Python: >=3.6
License-File: LICENSE
Requires-Dist: requests
Requires-Dist: websocket-client
Requires-Dist: websockets
Requires-Dist: dateparser==1.0.0
Requires-Dist: ecdsa==0.16.0
Requires-Dist: eth_keys
Requires-Dist: eth-account<0.6.0,>=0.4.0
Requires-Dist: mpmath==1.0.0
Requires-Dist: pytest<5.0.0,>=4.4.0
Requires-Dist: requests-mock==1.6.0
Requires-Dist: requests<3.0.0,>=2.22.0
Requires-Dist: setuptools
Requires-Dist: sympy==1.6
Requires-Dist: tox==3.13.2
Requires-Dist: web3<6.0.0,>=5.0.0
